requests_html2-2.0.3.dist-info/METADATA
requests_html2-2.0.3.dist-info/WHEEL
requests_html2.py
requests_html2-2.0.3.dist-info/RECORD
