Metadata-Version: 2.1
Name: requests_html2
Version: 2.0.3
Summary: HTML Parsing for Humans
Author-Email: Bevis <alonefire@foxmail.com>
License: MIT
Project-URL: Homepage, https://github.com/AloneFire/requests_html2
Project-URL: Bug tracker, https://github.com/AloneFire/requests_html2
Requires-Python: >=3.9
Requires-Dist: pyquery>=1.4.3
Requires-Dist: beautifulsoup4>=4.12.2
Requires-Dist: playwright>=1.37.0
Requires-Dist: httpx>=0.24.1
